[
  { 
    "name": "Spagehtthi Bollo",
    "base": "Noodles",
    "type": "Hauptspeise",
    "severity": 3.8,
    "ingrediants": ["Spagetthi", "Tomaten"],
    "description": "First you have to..."
  },
  {
    "name": "Mushroom Risotto",
    "base": "Rice",
    "type": "Hauptspeise",
    "severity": 4.5,
    "ingredients": ["Pilze", "Reis"],
    "description": "First you have to..."
  },
  {
    "name": "Vodka Martini",
    "base": "Vodka",
    "type": "Drink",
    "severity": 4.5,
    "ingredients": ["Vodka", "Martini"],
    "description": "First you have to..."
  },
  {
    "name": "Tomatensuppe",
    "base": "Tomaten",
    "type": "Vorspeise",
    "severity": 4.5,
    "ingredients": ["Tomaten", "Wasser"],
    "description": "First you have to..."
  },
  {
    "name": "Spargelsuppe",
    "base": "Spargel",
    "type": "Vorspeise",
    "severity": 4.5,
    "ingredients": ["Spargel", "Wasser"],
    "description": "First you have to..."
  },
  {
    "name": "Bier",
    "base": "Bier",
    "type": "Drink",
    "severity": 4.5,
    "ingredients": ["Hefe", "Wasser", "Hopfen"],
    "description": "First you have to..."
  },
  {
    "name": "Mamorkuchen",
    "base": "Teig",
    "type": "Dessert",
    "severity": 4.5,
    "ingredients": ["Hefe", "Wasser", "Schoko"],
    "description": "First you have to..."
  },
  {
    "name": "Teramisu",
    "base": "Teig",
    "type": "Dessert",
    "severity": 4.5,
    "ingredients": ["Hefe", "Wasser", "KaFFEE"],
    "description": "First you have to..."
  }
]
